{
	"conditions": [
		{
			"type": "forge:mod_loaded",
			"modid": "enemyexpansion"
		}
	],
    "entity": "enemyexpansion:slugger",
    "name": "entity.enemyexpansion.slugger",
    "name_color": "#3C5A52",
    "gui_scale": 0.8,
    "gui_x_offset": 0,
    "gui_y_offset": 0,
    "gui_z_offset": 0,
    "sim_cost": 128,
    "input": {
        "item": "hostilenetworks:prediction_matrix"
    },
    "base_drop": {
        "item": "hostilenetworks:overworld_prediction"
    },
    "trivia": "custom.trivia.slugger",
    "fabricator_drops": [
        {
            "item": "minecraft:rotten_flesh",
            "count": 64
        },
        {
            "item": "minecraft:iron_ingot",
            "count": 8
        },
        {
            "item": "minecraft:cooked_beef",
            "count": 16
        },
        {
            "item": "minecraft:baked_potato",
            "count": 16
        },
        {
            "optional": true,
            "item": "reliquary:zombie_heart",
            "count": 3
        }
    ]
}